<?xml version="1.0" encoding="UTF-8"?>
<con:soapui-project activeEnvironment="Default" name="Platform library 2.0.0" resourceRoot="" soapui-version="5.0.0" abortOnError="false" runType="SEQUENTIAL" xmlns:con="http://eviware.com/soapui/config"><con:settings/><con:interface xsi:type="con:WsdlInterface" wsaVersion="NONE" name="librarySoap12" type="wsdl" bindingName="{http://www.sample.com/Library/LibraryServiceMessages}librarySoap12" soapVersion="1_2" anonymous="optional" definition="http://localhost:8080/platform-library-2.0.0/services/library.wsdl" xmlns:xsi="http://www.w3.org/2001/XMLSchema-instance"><con:settings/><con:definitionCache type="TEXT" rootPart="http://localhost:8080/platform-library-2.0.0/services/library.wsdl"><con:part><con:url>http://localhost:8080/platform-library-2.0.0/services/library.wsdl</con:url><con:content><![CDATA[<wsdl:definitions targetNamespace="http://www.sample.com/Library/LibraryServiceMessages" xmlns:wsdl="http://schemas.xmlsoap.org/wsdl/" xmlns:sch0="http://www.sample.com/Library/LibraryServiceMessages" xmlns:sch1="http://www.qpark.com/CommonTypes" xmlns:sch2="http://www.samples.com/CommonTypes" xmlns:sch3="http://www.samples.com/Library/LibraryTypes" xmlns:sch4="http://www.qpark.com/Common/CommonServiceMessages" xmlns:soap12="http://schemas.xmlsoap.org/wsdl/soap12/" xmlns:tns="http://www.sample.com/Library/LibraryServiceMessages">
  <wsdl:types>
    <schema attributeFormDefault="unqualified" elementFormDefault="qualified" jaxb:version="2.1" targetNamespace="http://www.sample.com/Library/LibraryServiceMessages" xmlns="http://www.w3.org/2001/XMLSchema" xmlns:EIPctym="http://www.qpark.com/Common/CommonServiceMessages" xmlns:ISSlib="http://www.samples.com/Library/LibraryTypes" xmlns:ISSlibm="http://www.sample.com/Library/LibraryServiceMessages" xmlns:jaxb="http://java.sun.com/xml/ns/jaxb">
      <annotation>
        <appinfo>
          <jaxb:schemaBindings>
            <jaxb:package name="com.samples.platform.service.library.msg"/>
          </jaxb:schemaBindings>
        </appinfo>
        <documentation>
          <!--* Copyright (c) 2013, 2014, 2015 QPark Consulting  S.a r.l.
 * 
 * This program and the accompanying materials are made available under the 
 * terms of the Eclipse Public License v1.0. 
 * The Eclipse Public License is available at 
 * http://www.eclipse.org/legal/epl-v10.html.
 * 
 * Contributors:
 *     Bernhard Hausen - Initial API and implementation-->
          Message definitions of the library web service.
        </documentation>
      </annotation>
      <import namespace="http://www.samples.com/Library/LibraryTypes"/>
      <import namespace="http://www.qpark.com/Common/CommonServiceMessages"/>
      <complexType name="CreateBookRequestType">
        <complexContent>
          <extension base="EIPctym:RequestMessage">
            <sequence>
              <element maxOccurs="unbounded" name="book" type="ISSlib:BookType"/>
            </sequence>
          </extension>
        </complexContent>
      </complexType>
      <complexType name="CreateBookResponseType">
        <complexContent>
          <extension base="EIPctym:ResponseMessage">
            <sequence>
              <element maxOccurs="unbounded" minOccurs="0" name="book" type="ISSlib:BookType"/>
            </sequence>
          </extension>
        </complexContent>
      </complexType>
      <element name="CreateBookRequest" type="ISSlibm:CreateBookRequestType"/>
      <element name="CreateBookResponse" type="ISSlibm:CreateBookResponseType"/>
      <complexType name="GetBookRequestType">
        <complexContent>
          <extension base="EIPctym:RequestMessage">
            <sequence>
              <element name="criteria" type="ISSlib:BookCriteriaType"/>
            </sequence>
          </extension>
        </complexContent>
      </complexType>
      <complexType name="GetBookResponseType">
        <complexContent>
          <extension base="EIPctym:ResponseMessage">
            <sequence>
              <element maxOccurs="unbounded" minOccurs="0" name="book" type="ISSlib:BookType"/>
            </sequence>
          </extension>
        </complexContent>
      </complexType>
      <element name="GetBookRequest" type="ISSlibm:GetBookRequestType"/>
      <element name="GetBookResponse" type="ISSlibm:GetBookResponseType"/>
    </schema>
    <schema attributeFormDefault="unqualified" elementFormDefault="unqualified" jaxb:version="2.0" targetNamespace="http://www.qpark.com/CommonTypes" xmlns="http://www.w3.org/2001/XMLSchema" xmlns:EIPcty="http://www.qpark.com/CommonTypes" xmlns:jaxb="http://java.sun.com/xml/ns/jaxb">
      <annotation>
        <appinfo>
          <jaxb:schemaBindings>
            <jaxb:package name="com.qpark.eip.model.common"/>
          </jaxb:schemaBindings>
        </appinfo>
        <documentation></documentation>
      </annotation>
      <simpleType name="RegularExpressionType">
        <annotation>
          <documentation>A regular expression</documentation>
        </annotation>
        <restriction base="string"/>
      </simpleType>
      <simpleType name="ContainsSearchExpressionType">
        <annotation>
          <documentation>A search expression using the contains semantic.</documentation>
        </annotation>
        <restriction base="string"/>
      </simpleType>
      <simpleType name="UUIDType">
        <annotation>
          <documentation>A general unique identifier based on the Java implementation.
 			Every entity in the master data architecture needs an assigned UUID.</documentation>
        </annotation>
        <restriction base="normalizedString">
          <length fixed="true" value="36"/>
        </restriction>
      </simpleType>
      <complexType abstract="true" name="EntityType">
        <annotation>
          <documentation>Things in EIP</documentation>
        </annotation>
        <sequence>
          <element minOccurs="0" name="UUID" type="EIPcty:UUIDType">
            <annotation>
              <documentation>The UUID is a unique identifier of an object in a master data architecture. 
					The id is optional since it can be empty for entities to be saved in a system.</documentation>
            </annotation>
          </element>
        </sequence>
      </complexType>
      <complexType abstract="true" name="AssetType">
        <annotation>
          <documentation>Named things in EIP</documentation>
        </annotation>
        <complexContent>
          <extension base="EIPcty:EntityType">
            <sequence>
              <element name="name" type="string"/>
            </sequence>
          </extension>
        </complexContent>
      </complexType>
      <complexType abstract="true" name="EntityCriteriaType">
        <annotation>
          <documentation>Criteria for the entity search. 
A criteria complex type in general defines a set of search criteria. Search 
criteria are combined and each element adds a new restriction to the 
search. An empty sequence of elements for a criteria search retrieves
all entities. In general the string fields shall allow for a regular expression 
search that is compliant with the regular expression search in the back-end system.</documentation>
        </annotation>
        <sequence>
          <element maxOccurs="unbounded" minOccurs="0" name="id" type="EIPcty:UUIDType">
            <annotation>
              <documentation>The UUID of the object that shall be retrieved. The UUID is optional. 
					If no UUID is given the size of the search result set can be >1.</documentation>
            </annotation>
          </element>
          <element minOccurs="0" name="maxElements" type="integer">
            <annotation>
              <documentation>The maximum number of elements returned by the search.</documentation>
            </annotation>
          </element>
        </sequence>
      </complexType>
      <complexType abstract="true" name="AssetCriteriaType">
        <annotation>
          <documentation>Criteria for the entity search. 
A criteria complex type in general defines a set of search criteria. Search 
criteria are combined and each element adds a new restriction to the 
search. An empty sequence of elements for a criteria search retrieves
all entities. In general all fields shall allow for a regular expression search that 
is compliant with the regular expression search in back-end systems.</documentation>
        </annotation>
        <complexContent>
          <extension base="EIPcty:EntityCriteriaType">
            <sequence>
              <element minOccurs="0" name="name" type="EIPcty:RegularExpressionType">
                <annotation>
                  <documentation>The name of the object.</documentation>
                </annotation>
              </element>
            </sequence>
          </extension>
        </complexContent>
      </complexType>
      <complexType name="ReferenceDataType">
        <annotation>
          <documentation>Reference data maps to the master data enumerations. 
Enumerations allow for a flexible configuration of the the master data aware applications.</documentation>
        </annotation>
        <complexContent>
          <extension base="EIPcty:EntityType">
            <sequence>
              <element name="displayValue" type="string">
                <annotation>
                  <documentation>The display value shall be used to
								populate visual GUI elements.</documentation>
                </annotation>
              </element>
              <element name="category" type="string">
                <annotation>
                  <documentation>The category the reference data entry
								belongs to. The category is defined in
								the master system or in the enterprise integration platform itself.</documentation>
                </annotation>
              </element>
              <element minOccurs="0" name="description" type="string">
                <annotation>
                  <documentation>Description of the reference data entry.</documentation>
                </annotation>
              </element>
              <element name="active" type="boolean">
                <annotation>
                  <documentation>Flag indicating that the reference data
								entry is no longer active. It shall no
								longer be used in partner systems.</documentation>
                </annotation>
              </element>
              <element minOccurs="0" name="value" type="string"/>
            </sequence>
          </extension>
        </complexContent>
      </complexType>
      <complexType name="ReferenceDataCriteriaType">
        <annotation>
          <documentation>Criteria for the the reference data search.</documentation>
        </annotation>
        <complexContent>
          <extension base="EIPcty:EntityCriteriaType">
            <sequence>
              <element minOccurs="0" name="category" type="EIPcty:RegularExpressionType">
                <annotation>
                  <documentation>The category of the reference data that shall be retrieved. 
							If no category is defined all reference data entries are returned.</documentation>
                </annotation>
              </element>
              <element name="active" type="boolean">
                <annotation>
                  <documentation>Flag indicating that the reference data entry is no longer active. 
							It shall no longer be used in partner systems.</documentation>
                </annotation>
              </element>
            </sequence>
          </extension>
        </complexContent>
      </complexType>
      <complexType name="PropertyType">
        <annotation>
          <documentation>A key with a list of values.</documentation>
        </annotation>
        <sequence>
          <element name="name" type="string">
            <annotation>
              <documentation>The key.</documentation>
            </annotation>
          </element>
          <element maxOccurs="unbounded" minOccurs="0" name="value" type="string">
            <annotation>
              <documentation>The value assigned to the key.</documentation>
            </annotation>
          </element>
        </sequence>
      </complexType>
    </schema>
    <schema attributeFormDefault="unqualified" elementFormDefault="unqualified" jaxb:version="2.0" targetNamespace="http://www.samples.com/CommonTypes" xmlns="http://www.w3.org/2001/XMLSchema" xmlns:EIPcty="http://www.qpark.com/CommonTypes" xmlns:ISScty="http://www.samples.com/CommonTypes" xmlns:jaxb="http://java.sun.com/xml/ns/jaxb">
      <annotation>
        <appinfo>
          <jaxb:schemaBindings>
            <jaxb:package name="com.samples.platform.model.common"/>
          </jaxb:schemaBindings>
        </appinfo>
        <documentation>
          <!--* Copyright (c) 2013, 2014, 2015 QPark Consulting  S.a r.l.
 * 
 * This program and the accompanying materials are made available under the 
 * terms of the Eclipse Public License v1.0. 
 * The Eclipse Public License is available at 
 * http://www.eclipse.org/legal/epl-v10.html.
 * 
 * Contributors:
 *     Bernhard Hausen - Initial API and implementation-->
        </documentation>
      </annotation>
      <import namespace="http://www.qpark.com/CommonTypes"/>
      <simpleType name="EURType">
        <restriction base="decimal"/>
      </simpleType>
    </schema>
    <schema attributeFormDefault="unqualified" elementFormDefault="unqualified" jaxb:version="2.0" targetNamespace="http://www.samples.com/Library/LibraryTypes" xmlns="http://www.w3.org/2001/XMLSchema" xmlns:EIPcty="http://www.qpark.com/CommonTypes" xmlns:ISScty="http://www.samples.com/CommonTypes" xmlns:ISSlib="http://www.samples.com/Library/LibraryTypes" xmlns:jaxb="http://java.sun.com/xml/ns/jaxb">
      <annotation>
        <appinfo>
          <jaxb:schemaBindings>
            <jaxb:package name="com.samples.platform.model.library"/>
          </jaxb:schemaBindings>
        </appinfo>
        <documentation>
          <!--* Copyright (c) 2013, 2014, 2015 QPark Consulting  S.a r.l.
 * 
 * This program and the accompanying materials are made available under the 
 * terms of the Eclipse Public License v1.0. 
 * The Eclipse Public License is available at 
 * http://www.eclipse.org/legal/epl-v10.html.
 * 
 * Contributors:
 *     Bernhard Hausen - Initial API and implementation-->
        </documentation>
      </annotation>
      <import namespace="http://www.samples.com/CommonTypes"/>
      <import namespace="http://www.qpark.com/CommonTypes"/>
      <complexType name="BookType">
        <complexContent>
          <extension base="EIPcty:EntityType">
            <sequence>
              <element name="ISBN" type="string"/>
              <element name="title" type="string"/>
              <element name="price" type="ISScty:EURType"/>
              <element name="category" type="EIPcty:UUIDType"/>
              <element name="language" type="EIPcty:UUIDType"/>
            </sequence>
          </extension>
        </complexContent>
      </complexType>
      <complexType name="BookCriteriaType">
        <complexContent>
          <extension base="EIPcty:EntityCriteriaType">
            <sequence>
              <element name="ISBN" type="string"/>
            </sequence>
          </extension>
        </complexContent>
      </complexType>
      <complexType name="LibraryType">
        <complexContent>
          <extension base="EIPcty:AssetType">
            <sequence>
              <element minOccurs="0" name="location" type="string"/>
              <element maxOccurs="unbounded" minOccurs="0" name="books" type="ISSlib:BookType"/>
            </sequence>
          </extension>
        </complexContent>
      </complexType>
    </schema>
    <schema attributeFormDefault="unqualified" elementFormDefault="unqualified" jaxb:version="2.1" targetNamespace="http://www.qpark.com/Common/CommonServiceMessages" xmlns="http://www.w3.org/2001/XMLSchema" xmlns:EIPcty="http://www.qpark.com/CommonTypes" xmlns:EIPctym="http://www.qpark.com/Common/CommonServiceMessages" xmlns:jaxb="http://java.sun.com/xml/ns/jaxb">
      <annotation>
        <appinfo>
          <jaxb:schemaBindings>
            <jaxb:package name="com.qpark.eip.service.common.msg"/>
          </jaxb:schemaBindings>
        </appinfo>
        <documentation>Message definitions of the common web service.</documentation>
      </annotation>
      <import namespace="http://www.qpark.com/CommonTypes"/>
      <complexType name="ResponseMessage">
        <annotation>
          <documentation>Response</documentation>
        </annotation>
        <sequence>
          <element maxOccurs="unbounded" minOccurs="0" name="failure" type="EIPctym:FailureType">
            <annotation>
              <documentation>Failures that happened in the ESB</documentation>
            </annotation>
          </element>
        </sequence>
      </complexType>
      <complexType name="FailureType">
        <annotation>
          <documentation>The FailureType carries information about incidents that
				happened in the ESB Spring integration service operation
				gateways. In contrast to that the EIP returns SOAP
				faults in case of failures in the Spring Web Services
				and WebService security layer. These failures are
				maintained in the
				web-servlet.xmlSoapFaultMappingExceptionResolver bean
				mapping internal java exceptions to public EIP SOAP
				messages.</documentation>
        </annotation>
        <sequence>
          <element name="code" type="EIPctym:ErrorCode">
            <annotation>
              <documentation>The error code is intended to be used by the
						service desk to help the end user in resolving
						the issue. It shall be displayed with the
						userMessage.</documentation>
            </annotation>
          </element>
          <element name="userMessage" type="string">
            <annotation>
              <documentation>The user message is displayed to the end user,
						for example the EIP client. It describes the
						incident in a way the end user can understand
						and gives advice on how to deal with it.</documentation>
            </annotation>
          </element>
          <element name="errorDetails" type="string">
            <annotation>
              <documentation>Error details are intended to be logged in the
						Web Service client. Details contain the stack
						trace and further information about the incident
						on the EIP.</documentation>
            </annotation>
          </element>
          <element name="severity" type="EIPctym:Severity">
            <annotation>
              <documentation>The severity can be used by EIP clients to react
						on Service Bus incidents. For example the EIP
						client can retry the execution of operation. In
						general the design of the operations does not
						foresee a retry of operations. (note: this does
						not refer to retries in case the EIP is not
						operational. In that case there will be a client
						side exception.)</documentation>
            </annotation>
          </element>
        </sequence>
      </complexType>
      <simpleType name="Severity">
        <annotation>
          <documentation>Severity definition for failure types</documentation>
        </annotation>
        <restriction base="string">
          <enumeration value="WARNING"/>
          <enumeration value="ERROR"/>
        </restriction>
      </simpleType>
      <simpleType name="ErrorCode">
        <annotation>
          <documentation>Error codes define the type of error that happened in the service provider application.</documentation>
        </annotation>
        <restriction base="string">
          <enumeration value="E_ALL_NOT_KNOWN_ERROR"/>
        </restriction>
      </simpleType>
      <complexType name="RequestMessage">
        <annotation>
          <documentation>The RequestMessage is inherited by all (but one) request
				messages. The userName is part of all request messages
				since the service provider filters the response based on
				authorisation of the user.</documentation>
        </annotation>
        <sequence>
          <element name="userName" type="string">
            <annotation>
              <documentation>The EIP application user</documentation>
            </annotation>
          </element>
        </sequence>
      </complexType>
      <complexType name="GetServiceStatusRequestType">
        <annotation>
          <documentation>@ServiceConsumer ESB @ServiceImplementor ESB
				@ServiceDataProvider ESB @ServiceDescription returns the
				status of the service (connectivity to databases,
				external systems ...).</documentation>
        </annotation>
        <complexContent>
          <extension base="EIPctym:RequestMessage"/>
        </complexContent>
      </complexType>
      <complexType name="GetServiceStatusResponseType">
        <annotation>
          <documentation>The service status.</documentation>
        </annotation>
        <complexContent>
          <extension base="EIPctym:ResponseMessage">
            <sequence>
              <element name="status" type="string">
                <annotation>
                  <documentation>Status of the service.</documentation>
                </annotation>
              </element>
              <element maxOccurs="unbounded" minOccurs="0" name="details" type="EIPcty:PropertyType">
                <annotation>
                  <documentation>The details of the status.</documentation>
                </annotation>
              </element>
            </sequence>
          </extension>
        </complexContent>
      </complexType>
      <complexType name="GetReferenceDataRequestType">
        <annotation>
          <documentation>@ServiceConsumer
tbd
				@ServiceImplementor
ESB
				@ServiceDataProvider
ESB
				@ServiceDescription
GetReferenceData returns reference data definitions from the ESB core to resolve UUID references.</documentation>
        </annotation>
        <complexContent>
          <extension base="EIPctym:RequestMessage">
            <sequence>
              <element minOccurs="0" name="criteria">
                <annotation>
                  <documentation>Reference data search criteria</documentation>
                </annotation>
                <complexType>
                  <complexContent>
                    <extension base="EIPcty:ReferenceDataCriteriaType"/>
                  </complexContent>
                </complexType>
              </element>
            </sequence>
          </extension>
        </complexContent>
      </complexType>
      <complexType name="GetReferenceDataResponseType">
        <annotation>
          <documentation>Reference data from ESb enumerations.</documentation>
        </annotation>
        <complexContent>
          <extension base="EIPctym:ResponseMessage">
            <sequence>
              <element maxOccurs="unbounded" minOccurs="0" name="referenceData" type="EIPcty:ReferenceDataType">
                <annotation>
                  <documentation>Reference data</documentation>
                </annotation>
              </element>
            </sequence>
          </extension>
        </complexContent>
      </complexType>
      <element name="GetServiceStatusRequest" type="EIPctym:GetServiceStatusRequestType"/>
      <element name="GetServiceStatusResponse" type="EIPctym:GetServiceStatusResponseType"/>
      <element name="GetReferenceDataRequest" type="EIPctym:GetReferenceDataRequestType"/>
      <element name="GetReferenceDataResponse" type="EIPctym:GetReferenceDataResponseType"/>
    </schema>
  </wsdl:types>
  <wsdl:message name="CreateBookResponse">
    <wsdl:part element="tns:CreateBookResponse" name="CreateBookResponse"></wsdl:part>
  </wsdl:message>
  <wsdl:message name="GetServiceStatusRequest">
    <wsdl:part element="sch4:GetServiceStatusRequest" name="GetServiceStatusRequest"></wsdl:part>
  </wsdl:message>
  <wsdl:message name="GetReferenceDataRequest">
    <wsdl:part element="sch4:GetReferenceDataRequest" name="GetReferenceDataRequest"></wsdl:part>
  </wsdl:message>
  <wsdl:message name="GetBookResponse">
    <wsdl:part element="tns:GetBookResponse" name="GetBookResponse"></wsdl:part>
  </wsdl:message>
  <wsdl:message name="GetServiceStatusResponse">
    <wsdl:part element="sch4:GetServiceStatusResponse" name="GetServiceStatusResponse"></wsdl:part>
  </wsdl:message>
  <wsdl:message name="GetReferenceDataResponse">
    <wsdl:part element="sch4:GetReferenceDataResponse" name="GetReferenceDataResponse"></wsdl:part>
  </wsdl:message>
  <wsdl:message name="CreateBookRequest">
    <wsdl:part element="tns:CreateBookRequest" name="CreateBookRequest"></wsdl:part>
  </wsdl:message>
  <wsdl:message name="GetBookRequest">
    <wsdl:part element="tns:GetBookRequest" name="GetBookRequest"></wsdl:part>
  </wsdl:message>
  <wsdl:portType name="library">
    <wsdl:operation name="CreateBook">
      <wsdl:input message="tns:CreateBookRequest" name="CreateBookRequest"></wsdl:input>
      <wsdl:output message="tns:CreateBookResponse" name="CreateBookResponse"></wsdl:output>
    </wsdl:operation>
    <wsdl:operation name="GetServiceStatus">
      <wsdl:input message="tns:GetServiceStatusRequest" name="GetServiceStatusRequest"></wsdl:input>
      <wsdl:output message="tns:GetServiceStatusResponse" name="GetServiceStatusResponse"></wsdl:output>
    </wsdl:operation>
    <wsdl:operation name="GetReferenceData">
      <wsdl:input message="tns:GetReferenceDataRequest" name="GetReferenceDataRequest"></wsdl:input>
      <wsdl:output message="tns:GetReferenceDataResponse" name="GetReferenceDataResponse"></wsdl:output>
    </wsdl:operation>
    <wsdl:operation name="GetBook">
      <wsdl:input message="tns:GetBookRequest" name="GetBookRequest"></wsdl:input>
      <wsdl:output message="tns:GetBookResponse" name="GetBookResponse"></wsdl:output>
    </wsdl:operation>
  </wsdl:portType>
  <wsdl:binding name="librarySoap12" type="tns:library">
    <soap12:binding style="document" transport="http://schemas.xmlsoap.org/soap/http"/>
    <wsdl:operation name="CreateBook">
      <soap12:operation soapAction=""/>
      <wsdl:input name="CreateBookRequest">
        <soap12:body use="literal"/>
      </wsdl:input>
      <wsdl:output name="CreateBookResponse">
        <soap12:body use="literal"/>
      </wsdl:output>
    </wsdl:operation>
    <wsdl:operation name="GetServiceStatus">
      <soap12:operation soapAction=""/>
      <wsdl:input name="GetServiceStatusRequest">
        <soap12:body use="literal"/>
      </wsdl:input>
      <wsdl:output name="GetServiceStatusResponse">
        <soap12:body use="literal"/>
      </wsdl:output>
    </wsdl:operation>
    <wsdl:operation name="GetReferenceData">
      <soap12:operation soapAction=""/>
      <wsdl:input name="GetReferenceDataRequest">
        <soap12:body use="literal"/>
      </wsdl:input>
      <wsdl:output name="GetReferenceDataResponse">
        <soap12:body use="literal"/>
      </wsdl:output>
    </wsdl:operation>
    <wsdl:operation name="GetBook">
      <soap12:operation soapAction=""/>
      <wsdl:input name="GetBookRequest">
        <soap12:body use="literal"/>
      </wsdl:input>
      <wsdl:output name="GetBookResponse">
        <soap12:body use="literal"/>
      </wsdl:output>
    </wsdl:operation>
  </wsdl:binding>
  <wsdl:service name="libraryService">
    <wsdl:port binding="tns:librarySoap12" name="librarySoap12">
      <soap12:address location="http://localhost:8080/platform-library-2.0.0/services/library"/>
    </wsdl:port>
  </wsdl:service>
</wsdl:definitions>]]></con:content><con:type>http://schemas.xmlsoap.org/wsdl/</con:type></con:part></con:definitionCache><con:endpoints><con:endpoint>http://localhost:8080/platform-library-2.1.0/services/library</con:endpoint></con:endpoints><con:operation isOneWay="false" action="" name="CreateBook" bindingOperationName="CreateBook" type="Request-Response" outputName="CreateBookResponse" inputName="CreateBookRequest" receivesAttachments="false" sendsAttachments="false" anonymous="optional"><con:settings/><con:call name="Request 1" wssPasswordType="PasswordDigest" outgoingWss="" incomingWss=""><con:settings/><con:encoding>UTF-8</con:encoding><con:endpoint>http://localhost:8080/platform-library-2.1.0/services/library</con:endpoint><con:request><![CDATA[<soap:Envelope xmlns:soap="http://www.w3.org/2003/05/soap-envelope" xmlns:lib="http://www.sample.com/Library/LibraryServiceMessages">
   <soap:Header/>
   <soap:Body>
      <lib:CreateBookRequest>
         <userName>?</userName>
         <!--1 or more repetitions:-->
         <lib:book>
            <!--Optional:-->
            <UUID>?</UUID>
            <ISBN>?</ISBN>
            <title>?</title>
            <price>?</price>
            <category>?</category>
            <language>?</language>
         </lib:book>
      </lib:CreateBookRequest>
   </soap:Body>
</soap:Envelope>]]></con:request><con:credentials><con:username>bus</con:username><con:password>password</con:password><con:domain xsi:nil="true"/><con:authType>No Authorization</con:authType></con:credentials><con:jmsConfig JMSDeliveryMode="PERSISTENT"/><con:jmsPropertyConfig/><con:wsaConfig mustUnderstand="NONE" version="200508" action="http://www.sample.com/Library/LibraryServiceMessages/library/CreateBookRequest"/><con:wsrmConfig version="1.2"/></con:call><con:call name="create" wssPasswordType="PasswordDigest" outgoingWss="" incomingWss=""><con:settings><con:setting id="com.eviware.soapui.impl.wsdl.WsdlRequest@request-headers">&lt;xml-fragment/></con:setting></con:settings><con:encoding>UTF-8</con:encoding><con:endpoint>http://localhost:8080/platform-library-2.1.0/services/library</con:endpoint><con:request><![CDATA[<soap:Envelope xmlns:soap="http://www.w3.org/2003/05/soap-envelope" xmlns:lib="http://www.sample.com/Library/LibraryServiceMessages">
   <soap:Header/>
   <soap:Body>
      <lib:CreateBookRequest>
         <userName>xljb</userName>
         <lib:book>
<UUID>157B9F3B78170152CF14486349238822</UUID>
<ISBN>157B9F3B78170152CF14486349238801</ISBN>
<title>Title 157B9F3B78170152CF14486349238801</title>
<price>10</price>
<category>Category</category>
<language>Language</language>
         </lib:book>
      </lib:CreateBookRequest>
   </soap:Body>
</soap:Envelope>]]></con:request><con:credentials><con:username>bus</con:username><con:password>password</con:password><con:domain xsi:nil="true"/><con:authType>No Authorization</con:authType></con:credentials><con:jmsConfig JMSDeliveryMode="PERSISTENT"/><con:jmsPropertyConfig/><con:wsaConfig mustUnderstand="NONE" version="200508" action="http://www.sample.com/Library/LibraryServiceMessages/library/CreateBookRequest"/><con:wsrmConfig version="1.2"/></con:call></con:operation><con:operation isOneWay="false" action="" name="GetBook" bindingOperationName="GetBook" type="Request-Response" outputName="GetBookResponse" inputName="GetBookRequest" receivesAttachments="false" sendsAttachments="false" anonymous="optional"><con:settings/><con:call name="Request 1" wssPasswordType="PasswordDigest" outgoingWss="" incomingWss=""><con:settings><con:setting id="com.eviware.soapui.impl.wsdl.WsdlRequest@request-headers">&lt;xml-fragment/></con:setting></con:settings><con:encoding>UTF-8</con:encoding><con:endpoint>http://localhost:8080/platform-library-2.1.0/services/library</con:endpoint><con:request><![CDATA[<soap:Envelope xmlns:soap="http://www.w3.org/2003/05/soap-envelope" xmlns:lib="http://www.sample.com/Library/LibraryServiceMessages">
   <soap:Header/>
   <soap:Body>
      <lib:GetBookRequest>
         <userName>?</userName>
         <lib:criteria>
            <!--Zero or more repetitions:-->
            <id>?</id>
            <!--Optional:-->
            <maxElements>?</maxElements>
            <ISBN>?</ISBN>
         </lib:criteria>
      </lib:GetBookRequest>
   </soap:Body>
</soap:Envelope>]]></con:request><con:credentials><con:username>bus</con:username><con:password>password</con:password><con:domain xsi:nil="true"/><con:authType>No Authorization</con:authType></con:credentials><con:jmsConfig JMSDeliveryMode="PERSISTENT"/><con:jmsPropertyConfig/><con:wsaConfig mustUnderstand="NONE" version="200508" action="http://www.sample.com/Library/LibraryServiceMessages/library/GetBookRequest"/><con:wsrmConfig version="1.2"/></con:call></con:operation><con:operation isOneWay="false" action="" name="GetReferenceData" bindingOperationName="GetReferenceData" type="Request-Response" outputName="GetReferenceDataResponse" inputName="GetReferenceDataRequest" receivesAttachments="false" sendsAttachments="false" anonymous="optional"><con:settings/><con:call name="Request 1" wssPasswordType="PasswordDigest" outgoingWss="" incomingWss=""><con:settings><con:setting id="com.eviware.soapui.impl.wsdl.WsdlRequest@request-headers">&lt;xml-fragment/></con:setting></con:settings><con:encoding>UTF-8</con:encoding><con:endpoint>http://localhost:8080/platform-library-2.1.0/services/library</con:endpoint><con:request><![CDATA[<soap:Envelope xmlns:soap="http://www.w3.org/2003/05/soap-envelope" xmlns:com="http://www.qpark.com/Common/CommonServiceMessages">
   <soap:Header/>
   <soap:Body>
      <com:GetReferenceDataRequest>
         <userName>?</userName>
         <!--Optional:-->
         <criteria>
            <!--Zero or more repetitions:-->
            <id>?</id>
            <!--Optional:-->
            <maxElements>?</maxElements>
            <!--Optional:-->
            <category>?</category>
            <active>?</active>
         </criteria>
      </com:GetReferenceDataRequest>
   </soap:Body>
</soap:Envelope>]]></con:request><con:credentials><con:username>bus</con:username><con:password>password</con:password><con:domain xsi:nil="true"/><con:authType>No Authorization</con:authType></con:credentials><con:jmsConfig JMSDeliveryMode="PERSISTENT"/><con:jmsPropertyConfig/><con:wsaConfig mustUnderstand="NONE" version="200508" action="http://www.sample.com/Library/LibraryServiceMessages/library/GetReferenceDataRequest"/><con:wsrmConfig version="1.2"/></con:call></con:operation><con:operation isOneWay="false" action="" name="GetServiceStatus" bindingOperationName="GetServiceStatus" type="Request-Response" outputName="GetServiceStatusResponse" inputName="GetServiceStatusRequest" receivesAttachments="false" sendsAttachments="false" anonymous="optional"><con:settings/><con:call name="Request 1" wssPasswordType="PasswordDigest" outgoingWss="" incomingWss=""><con:settings><con:setting id="com.eviware.soapui.impl.wsdl.WsdlRequest@request-headers">&lt;xml-fragment/></con:setting></con:settings><con:encoding>UTF-8</con:encoding><con:endpoint>http://localhost:8080/platform-library-2.1.0/services/library</con:endpoint><con:request><![CDATA[<soap:Envelope xmlns:soap="http://www.w3.org/2003/05/soap-envelope" xmlns:com="http://www.qpark.com/Common/CommonServiceMessages">
   <soap:Header/>
   <soap:Body>
      <com:GetServiceStatusRequest>
         <userName>?</userName>
      </com:GetServiceStatusRequest>
   </soap:Body>
</soap:Envelope>]]></con:request><con:credentials><con:username>bus</con:username><con:password>password</con:password><con:domain xsi:nil="true"/><con:authType>No Authorization</con:authType></con:credentials><con:jmsConfig JMSDeliveryMode="PERSISTENT"/><con:jmsPropertyConfig/><con:wsaConfig mustUnderstand="NONE" version="200508" action="http://www.sample.com/Library/LibraryServiceMessages/library/GetServiceStatusRequest"/><con:wsrmConfig version="1.2"/></con:call></con:operation></con:interface><con:interface xsi:type="con:WsdlInterface" wsaVersion="NONE" name="iss.tech.supportSoap12" type="wsdl" bindingName="{http://www.samples.com/TechnicalSupport/TechnicalSupportServiceMessages}iss.tech.supportSoap12" soapVersion="1_2" anonymous="optional" definition="http://localhost:8080/platform-library-2.0.0/services/iss.tech.support.wsdl" xmlns:xsi="http://www.w3.org/2001/XMLSchema-instance"><con:settings/><con:definitionCache type="TEXT" rootPart="http://localhost:8080/platform-library-2.0.0/services/iss.tech.support.wsdl"><con:part><con:url>http://localhost:8080/platform-library-2.0.0/services/iss.tech.support.wsdl</con:url><con:content><![CDATA[<wsdl:definitions targetNamespace="http://www.samples.com/TechnicalSupport/TechnicalSupportServiceMessages" xmlns:wsdl="http://schemas.xmlsoap.org/wsdl/" xmlns:sch0="http://www.samples.com/TechnicalSupport/TechnicalSupportServiceMessages" xmlns:sch1="http://www.qpark.com/CommonTypes" xmlns:sch2="http://www.samples.com/CommonTypes" xmlns:sch3="http://www.samples.com/TechnicalSupport/TechnicalSupportTypes" xmlns:sch4="http://www.qpark.com/Common/CommonServiceMessages" xmlns:soap12="http://schemas.xmlsoap.org/wsdl/soap12/" xmlns:tns="http://www.samples.com/TechnicalSupport/TechnicalSupportServiceMessages">
  <wsdl:types>
    <schema attributeFormDefault="unqualified" elementFormDefault="unqualified" jaxb:version="2.0" targetNamespace="http://www.samples.com/TechnicalSupport/TechnicalSupportServiceMessages" xmlns="http://www.w3.org/2001/XMLSchema" xmlns:EIPcty="http://www.qpark.com/CommonTypes" xmlns:EIPctym="http://www.qpark.com/Common/CommonServiceMessages" xmlns:ISSTechSupport="http://www.samples.com/TechnicalSupport/TechnicalSupportTypes" xmlns:ISSTechSupportm="http://www.samples.com/TechnicalSupport/TechnicalSupportServiceMessages" xmlns:ISScty="http://www.samples.com/CommonTypes" xmlns:jaxb="http://java.sun.com/xml/ns/jaxb">
      <annotation>
        <appinfo>
          <jaxb:schemaBindings>
            <jaxb:package name="com.samples.platform.service.iss.tech.support.msg"/>
          </jaxb:schemaBindings>
        </appinfo>
        <documentation>
          <!--* Copyright (c) 2013, 2014, 2015 QPark Consulting  S.a r.l.
 * 
 * This program and the accompanying materials are made available under the 
 * terms of the Eclipse Public License v1.0. 
 * The Eclipse Public License is available at 
 * http://www.eclipse.org/legal/epl-v10.html.
 * 
 * Contributors:
 *     Bernhard Hausen - Initial API and implementation-->
          Message definitions of the common web service.
        </documentation>
      </annotation>
      <import namespace="http://www.qpark.com/CommonTypes"/>
      <import namespace="http://www.samples.com/CommonTypes"/>
      <import namespace="http://www.samples.com/TechnicalSupport/TechnicalSupportTypes"/>
      <import namespace="http://www.qpark.com/Common/CommonServiceMessages"/>
      <complexType name="GetAggregatedReferenceDataRequestType">
        <annotation>
          <documentation>@ServiceConsumer tbd
				@ServiceImplementor ESB
				@ServiceDataProvider ESB
				@ServiceDescription Example of the an aggregated GetReferenceData call.</documentation>
        </annotation>
        <complexContent>
          <extension base="EIPctym:RequestMessage">
            <sequence>
              <element name="criteria" type="EIPcty:ReferenceDataCriteriaType"/>
            </sequence>
          </extension>
        </complexContent>
      </complexType>
      <complexType name="GetAggregatedReferenceDataResponseType">
        <complexContent>
          <extension base="EIPctym:ResponseMessage">
            <sequence>
              <element maxOccurs="unbounded" minOccurs="0" name="referenceData" type="EIPcty:ReferenceDataType"/>
            </sequence>
          </extension>
        </complexContent>
      </complexType>
      <element name="GetAggregatedReferenceDataRequest" type="ISSTechSupportm:GetAggregatedReferenceDataRequestType"/>
      <element name="GetAggregatedReferenceDataResponse" type="ISSTechSupportm:GetAggregatedReferenceDataResponseType"/>
      <complexType name="GetForwardedReferenceDataRequestType">
        <annotation>
          <documentation>@ServiceConsumer tbd
				@ServiceImplementor ESB
				@ServiceDataProvider ESB
				@ServiceDescription Example of the an Forwarded GetReferenceData call.</documentation>
        </annotation>
        <complexContent>
          <extension base="EIPctym:RequestMessage">
            <sequence>
              <element name="criteria" type="EIPcty:ReferenceDataCriteriaType"/>
            </sequence>
          </extension>
        </complexContent>
      </complexType>
      <complexType name="GetForwardedReferenceDataResponseType">
        <complexContent>
          <extension base="EIPctym:ResponseMessage">
            <sequence>
              <element maxOccurs="unbounded" minOccurs="0" name="referenceData" type="EIPcty:ReferenceDataType"/>
            </sequence>
          </extension>
        </complexContent>
      </complexType>
      <element name="GetForwardedReferenceDataRequest" type="ISSTechSupportm:GetForwardedReferenceDataRequestType"/>
      <element name="GetForwardedReferenceDataResponse" type="ISSTechSupportm:GetForwardedReferenceDataResponseType"/>
      <complexType name="GetSystemUserReportRequestType">
        <annotation>
          <documentation>@ServiceConsumer tbd
				@ServiceImplementor ESB
				@ServiceDataProvider ESB
				@ServiceDescription Get the system user log report entries.</documentation>
        </annotation>
        <complexContent>
          <extension base="EIPctym:RequestMessage">
            <sequence>
              <element name="criteria" type="ISSTechSupport:SystemUserReportCriteriaType"/>
            </sequence>
          </extension>
        </complexContent>
      </complexType>
      <complexType name="GetSystemUserReportResponseType">
        <complexContent>
          <extension base="EIPctym:ResponseMessage">
            <sequence>
              <element maxOccurs="unbounded" minOccurs="0" name="report" type="ISSTechSupport:SystemUserReportType"/>
            </sequence>
          </extension>
        </complexContent>
      </complexType>
      <element name="GetSystemUserReportRequest" type="ISSTechSupportm:GetSystemUserReportRequestType"/>
      <element name="GetSystemUserReportResponse" type="ISSTechSupportm:GetSystemUserReportResponseType"/>
      <complexType name="GetOperationReportRequestType">
        <annotation>
          <documentation>@ServiceConsumer tbd
				@ServiceImplementor ESB
				@ServiceDataProvider ESB
				@ServiceDescription Get the system user log report entries.</documentation>
        </annotation>
        <complexContent>
          <extension base="EIPctym:RequestMessage">
            <sequence>
              <element name="criteria" type="ISSTechSupport:OperationReportCriteriaType"/>
            </sequence>
          </extension>
        </complexContent>
      </complexType>
      <complexType name="GetOperationReportResponseType">
        <complexContent>
          <extension base="EIPctym:ResponseMessage">
            <sequence>
              <element maxOccurs="unbounded" minOccurs="0" name="report" type="ISSTechSupport:OperationReportType"/>
            </sequence>
          </extension>
        </complexContent>
      </complexType>
      <element name="GetOperationReportRequest" type="ISSTechSupportm:GetOperationReportRequestType"/>
      <element name="GetOperationReportResponse" type="ISSTechSupportm:GetOperationReportResponseType"/>
      <complexType name="GetFlowReportRequestType">
        <annotation>
          <documentation>@ServiceConsumer tbd
				@ServiceImplementor ESB
				@ServiceDataProvider ESB
				@ServiceDescription Get the flow log messages reported.</documentation>
        </annotation>
        <complexContent>
          <extension base="EIPctym:RequestMessage">
            <sequence>
              <element name="criteria" type="ISSTechSupport:FlowReportCriteriaType"/>
            </sequence>
          </extension>
        </complexContent>
      </complexType>
      <complexType name="GetFlowReportResponseType">
        <complexContent>
          <extension base="EIPctym:ResponseMessage">
            <sequence>
              <element maxOccurs="unbounded" minOccurs="0" name="report" type="ISSTechSupport:FlowReportType"/>
            </sequence>
          </extension>
        </complexContent>
      </complexType>
      <element name="GetFlowReportRequest" type="ISSTechSupportm:GetFlowReportRequestType"/>
      <element name="GetFlowReportResponse" type="ISSTechSupportm:GetFlowReportResponseType"/>
    </schema>
    <schema attributeFormDefault="unqualified" elementFormDefault="unqualified" jaxb:version="2.0" targetNamespace="http://www.qpark.com/CommonTypes" xmlns="http://www.w3.org/2001/XMLSchema" xmlns:EIPcty="http://www.qpark.com/CommonTypes" xmlns:jaxb="http://java.sun.com/xml/ns/jaxb">
      <annotation>
        <appinfo>
          <jaxb:schemaBindings>
            <jaxb:package name="com.qpark.eip.model.common"/>
          </jaxb:schemaBindings>
        </appinfo>
        <documentation></documentation>
      </annotation>
      <simpleType name="RegularExpressionType">
        <annotation>
          <documentation>A regular expression</documentation>
        </annotation>
        <restriction base="string"/>
      </simpleType>
      <simpleType name="ContainsSearchExpressionType">
        <annotation>
          <documentation>A search expression using the contains semantic.</documentation>
        </annotation>
        <restriction base="string"/>
      </simpleType>
      <simpleType name="UUIDType">
        <annotation>
          <documentation>A general unique identifier based on the Java implementation.
 			Every entity in the master data architecture needs an assigned UUID.</documentation>
        </annotation>
        <restriction base="normalizedString">
          <length fixed="true" value="36"/>
        </restriction>
      </simpleType>
      <complexType abstract="true" name="EntityType">
        <annotation>
          <documentation>Things in EIP</documentation>
        </annotation>
        <sequence>
          <element minOccurs="0" name="UUID" type="EIPcty:UUIDType">
            <annotation>
              <documentation>The UUID is a unique identifier of an object in a master data architecture. 
					The id is optional since it can be empty for entities to be saved in a system.</documentation>
            </annotation>
          </element>
        </sequence>
      </complexType>
      <complexType abstract="true" name="AssetType">
        <annotation>
          <documentation>Named things in EIP</documentation>
        </annotation>
        <complexContent>
          <extension base="EIPcty:EntityType">
            <sequence>
              <element name="name" type="string"/>
            </sequence>
          </extension>
        </complexContent>
      </complexType>
      <complexType abstract="true" name="EntityCriteriaType">
        <annotation>
          <documentation>Criteria for the entity search. 
A criteria complex type in general defines a set of search criteria. Search 
criteria are combined and each element adds a new restriction to the 
search. An empty sequence of elements for a criteria search retrieves
all entities. In general the string fields shall allow for a regular expression 
search that is compliant with the regular expression search in the back-end system.</documentation>
        </annotation>
        <sequence>
          <element maxOccurs="unbounded" minOccurs="0" name="id" type="EIPcty:UUIDType">
            <annotation>
              <documentation>The UUID of the object that shall be retrieved. The UUID is optional. 
					If no UUID is given the size of the search result set can be >1.</documentation>
            </annotation>
          </element>
          <element minOccurs="0" name="maxElements" type="integer">
            <annotation>
              <documentation>The maximum number of elements returned by the search.</documentation>
            </annotation>
          </element>
        </sequence>
      </complexType>
      <complexType abstract="true" name="AssetCriteriaType">
        <annotation>
          <documentation>Criteria for the entity search. 
A criteria complex type in general defines a set of search criteria. Search 
criteria are combined and each element adds a new restriction to the 
search. An empty sequence of elements for a criteria search retrieves
all entities. In general all fields shall allow for a regular expression search that 
is compliant with the regular expression search in back-end systems.</documentation>
        </annotation>
        <complexContent>
          <extension base="EIPcty:EntityCriteriaType">
            <sequence>
              <element minOccurs="0" name="name" type="EIPcty:RegularExpressionType">
                <annotation>
                  <documentation>The name of the object.</documentation>
                </annotation>
              </element>
            </sequence>
          </extension>
        </complexContent>
      </complexType>
      <complexType name="ReferenceDataType">
        <annotation>
          <documentation>Reference data maps to the master data enumerations. 
Enumerations allow for a flexible configuration of the the master data aware applications.</documentation>
        </annotation>
        <complexContent>
          <extension base="EIPcty:EntityType">
            <sequence>
              <element name="displayValue" type="string">
                <annotation>
                  <documentation>The display value shall be used to
								populate visual GUI elements.</documentation>
                </annotation>
              </element>
              <element name="category" type="string">
                <annotation>
                  <documentation>The category the reference data entry
								belongs to. The category is defined in
								the master system or in the enterprise integration platform itself.</documentation>
                </annotation>
              </element>
              <element minOccurs="0" name="description" type="string">
                <annotation>
                  <documentation>Description of the reference data entry.</documentation>
                </annotation>
              </element>
              <element name="active" type="boolean">
                <annotation>
                  <documentation>Flag indicating that the reference data
								entry is no longer active. It shall no
								longer be used in partner systems.</documentation>
                </annotation>
              </element>
              <element minOccurs="0" name="value" type="string"/>
            </sequence>
          </extension>
        </complexContent>
      </complexType>
      <complexType name="ReferenceDataCriteriaType">
        <annotation>
          <documentation>Criteria for the the reference data search.</documentation>
        </annotation>
        <complexContent>
          <extension base="EIPcty:EntityCriteriaType">
            <sequence>
              <element minOccurs="0" name="category" type="EIPcty:RegularExpressionType">
                <annotation>
                  <documentation>The category of the reference data that shall be retrieved. 
							If no category is defined all reference data entries are returned.</documentation>
                </annotation>
              </element>
              <element name="active" type="boolean">
                <annotation>
                  <documentation>Flag indicating that the reference data entry is no longer active. 
							It shall no longer be used in partner systems.</documentation>
                </annotation>
              </element>
            </sequence>
          </extension>
        </complexContent>
      </complexType>
      <complexType name="PropertyType">
        <annotation>
          <documentation>A key with a list of values.</documentation>
        </annotation>
        <sequence>
          <element name="name" type="string">
            <annotation>
              <documentation>The key.</documentation>
            </annotation>
          </element>
          <element maxOccurs="unbounded" minOccurs="0" name="value" type="string">
            <annotation>
              <documentation>The value assigned to the key.</documentation>
            </annotation>
          </element>
        </sequence>
      </complexType>
    </schema>
    <schema attributeFormDefault="unqualified" elementFormDefault="unqualified" jaxb:version="2.0" targetNamespace="http://www.samples.com/CommonTypes" xmlns="http://www.w3.org/2001/XMLSchema" xmlns:EIPcty="http://www.qpark.com/CommonTypes" xmlns:ISScty="http://www.samples.com/CommonTypes" xmlns:jaxb="http://java.sun.com/xml/ns/jaxb">
      <annotation>
        <appinfo>
          <jaxb:schemaBindings>
            <jaxb:package name="com.samples.platform.model.iss.common"/>
          </jaxb:schemaBindings>
        </appinfo>
        <documentation>
          <!--* Copyright (c) 2013, 2014, 2015 QPark Consulting  S.a r.l.
 * 
 * This program and the accompanying materials are made available under the 
 * terms of the Eclipse Public License v1.0. 
 * The Eclipse Public License is available at 
 * http://www.eclipse.org/legal/epl-v10.html.
 * 
 * Contributors:
 *     Bernhard Hausen - Initial API and implementation-->
        </documentation>
      </annotation>
      <import namespace="http://www.qpark.com/CommonTypes"/>
      <simpleType name="EURType">
        <restriction base="decimal"/>
      </simpleType>
    </schema>
    <schema attributeFormDefault="unqualified" elementFormDefault="unqualified" jaxb:version="2.0" targetNamespace="http://www.samples.com/TechnicalSupport/TechnicalSupportTypes" xmlns="http://www.w3.org/2001/XMLSchema" xmlns:EIPcty="http://www.qpark.com/CommonTypes" xmlns:ISSTechSupport="http://www.samples.com/TechnicalSupport/TechnicalSupportTypes" xmlns:ISScty="http://www.samples.com/CommonTypes" xmlns:jaxb="http://java.sun.com/xml/ns/jaxb">
      <annotation>
        <appinfo>
          <jaxb:schemaBindings>
            <jaxb:package name="com.samples.platform.model.iss.tech.support"/>
          </jaxb:schemaBindings>
        </appinfo>
      </annotation>
      <import namespace="http://www.samples.com/CommonTypes"/>
      <import namespace="http://www.qpark.com/CommonTypes"/>
      <complexType name="SystemUserReportCriteriaType">
        <sequence>
          <element minOccurs="0" name="date" type="date"/>
        </sequence>
      </complexType>
      <complexType name="SystemUserReportType">
        <sequence>
          <element name="date" type="date"/>
          <element name="service" type="normalizedString"/>
          <element name="operation" type="normalizedString"/>
          <element name="serviceProvider" type="normalizedString"/>
          <element name="version" type="normalizedString"/>
          <element name="consumerSystemUser" type="normalizedString"/>
          <element name="requests" type="long"/>
          <element name="requestsDenied" type="long"/>
          <element name="errors" type="long"/>
        </sequence>
      </complexType>
      <complexType name="OperationReportCriteriaType">
        <sequence>
          <element minOccurs="0" name="service" type="normalizedString"/>
          <element minOccurs="0" name="operation" type="normalizedString"/>
          <element minOccurs="0" name="consumerName" type="normalizedString"/>
        </sequence>
      </complexType>
      <complexType name="OperationReportType">
        <sequence>
          <element name="date" type="dateTime"/>
          <element name="serviceProvider" type="normalizedString"/>
          <element name="service" type="normalizedString"/>
          <element name="operation" type="normalizedString"/>
          <element name="version" type="normalizedString"/>
          <element name="consumerName" type="normalizedString"/>
          <element name="consumerHost" type="normalizedString"/>
          <element name="duration" type="normalizedString"/>
        </sequence>
      </complexType>
      <complexType name="FlowReportCriteriaType">
        <sequence>
          <element name="start" type="dateTime"/>
          <element minOccurs="0" name="end" type="dateTime"/>
        </sequence>
      </complexType>
      <complexType name="FlowReportType">
        <sequence>
          <element name="flowSessionId" type="EIPcty:UUIDType"/>
          <element name="logTime" type="dateTime"/>
          <element name="severity" type="normalizedString"/>
          <element name="flowName" type="normalizedString"/>
          <element name="flowStep" type="normalizedString"/>
          <element name="messageClassification" type="normalizedString"/>
          <element name="additionalInformation" type="string"/>
          <element name="messageType" type="normalizedString"/>
          <element name="data" type="string"/>
        </sequence>
      </complexType>
    </schema>
    <schema attributeFormDefault="unqualified" elementFormDefault="unqualified" jaxb:version="2.1" targetNamespace="http://www.qpark.com/Common/CommonServiceMessages" xmlns="http://www.w3.org/2001/XMLSchema" xmlns:EIPcty="http://www.qpark.com/CommonTypes" xmlns:EIPctym="http://www.qpark.com/Common/CommonServiceMessages" xmlns:jaxb="http://java.sun.com/xml/ns/jaxb">
      <annotation>
        <appinfo>
          <jaxb:schemaBindings>
            <jaxb:package name="com.qpark.eip.service.common.msg"/>
          </jaxb:schemaBindings>
        </appinfo>
        <documentation>Message definitions of the common web service.</documentation>
      </annotation>
      <import namespace="http://www.qpark.com/CommonTypes"/>
      <complexType name="ResponseMessage">
        <annotation>
          <documentation>Response</documentation>
        </annotation>
        <sequence>
          <element maxOccurs="unbounded" minOccurs="0" name="failure" type="EIPctym:FailureType">
            <annotation>
              <documentation>Failures that happened in the ESB</documentation>
            </annotation>
          </element>
        </sequence>
      </complexType>
      <complexType name="FailureType">
        <annotation>
          <documentation>The FailureType carries information about incidents that
				happened in the ESB Spring integration service operation
				gateways. In contrast to that the EIP returns SOAP
				faults in case of failures in the Spring Web Services
				and WebService security layer. These failures are
				maintained in the
				web-servlet.xmlSoapFaultMappingExceptionResolver bean
				mapping internal java exceptions to public EIP SOAP
				messages.</documentation>
        </annotation>
        <sequence>
          <element name="code" type="EIPctym:ErrorCode">
            <annotation>
              <documentation>The error code is intended to be used by the
						service desk to help the end user in resolving
						the issue. It shall be displayed with the
						userMessage.</documentation>
            </annotation>
          </element>
          <element name="userMessage" type="string">
            <annotation>
              <documentation>The user message is displayed to the end user,
						for example the EIP client. It describes the
						incident in a way the end user can understand
						and gives advice on how to deal with it.</documentation>
            </annotation>
          </element>
          <element name="errorDetails" type="string">
            <annotation>
              <documentation>Error details are intended to be logged in the
						Web Service client. Details contain the stack
						trace and further information about the incident
						on the EIP.</documentation>
            </annotation>
          </element>
          <element name="severity" type="EIPctym:Severity">
            <annotation>
              <documentation>The severity can be used by EIP clients to react
						on Service Bus incidents. For example the EIP
						client can retry the execution of operation. In
						general the design of the operations does not
						foresee a retry of operations. (note: this does
						not refer to retries in case the EIP is not
						operational. In that case there will be a client
						side exception.)</documentation>
            </annotation>
          </element>
        </sequence>
      </complexType>
      <simpleType name="Severity">
        <annotation>
          <documentation>Severity definition for failure types</documentation>
        </annotation>
        <restriction base="string">
          <enumeration value="WARNING"/>
          <enumeration value="ERROR"/>
        </restriction>
      </simpleType>
      <simpleType name="ErrorCode">
        <annotation>
          <documentation>Error codes define the type of error that happened in the service provider application.</documentation>
        </annotation>
        <restriction base="string">
          <enumeration value="E_ALL_NOT_KNOWN_ERROR"/>
        </restriction>
      </simpleType>
      <complexType name="RequestMessage">
        <annotation>
          <documentation>The RequestMessage is inherited by all (but one) request
				messages. The userName is part of all request messages
				since the service provider filters the response based on
				authorisation of the user.</documentation>
        </annotation>
        <sequence>
          <element name="userName" type="string">
            <annotation>
              <documentation>The EIP application user</documentation>
            </annotation>
          </element>
        </sequence>
      </complexType>
      <complexType name="GetServiceStatusRequestType">
        <annotation>
          <documentation>@ServiceConsumer ESB @ServiceImplementor ESB
				@ServiceDataProvider ESB @ServiceDescription returns the
				status of the service (connectivity to databases,
				external systems ...).</documentation>
        </annotation>
        <complexContent>
          <extension base="EIPctym:RequestMessage"/>
        </complexContent>
      </complexType>
      <complexType name="GetServiceStatusResponseType">
        <annotation>
          <documentation>The service status.</documentation>
        </annotation>
        <complexContent>
          <extension base="EIPctym:ResponseMessage">
            <sequence>
              <element name="status" type="string">
                <annotation>
                  <documentation>Status of the service.</documentation>
                </annotation>
              </element>
              <element maxOccurs="unbounded" minOccurs="0" name="details" type="EIPcty:PropertyType">
                <annotation>
                  <documentation>The details of the status.</documentation>
                </annotation>
              </element>
            </sequence>
          </extension>
        </complexContent>
      </complexType>
      <complexType name="GetReferenceDataRequestType">
        <annotation>
          <documentation>@ServiceConsumer
tbd
				@ServiceImplementor
ESB
				@ServiceDataProvider
ESB
				@ServiceDescription
GetReferenceData returns reference data definitions from the ESB core to resolve UUID references.</documentation>
        </annotation>
        <complexContent>
          <extension base="EIPctym:RequestMessage">
            <sequence>
              <element name="criteria" type="EIPcty:ReferenceDataCriteriaType">
                <annotation>
                  <documentation>Reference data search criteria</documentation>
                </annotation>
              </element>
            </sequence>
          </extension>
        </complexContent>
      </complexType>
      <complexType name="GetReferenceDataResponseType">
        <annotation>
          <documentation>Reference data from ESb enumerations.</documentation>
        </annotation>
        <complexContent>
          <extension base="EIPctym:ResponseMessage">
            <sequence>
              <element maxOccurs="unbounded" minOccurs="0" name="referenceData" type="EIPcty:ReferenceDataType">
                <annotation>
                  <documentation>Reference data</documentation>
                </annotation>
              </element>
            </sequence>
          </extension>
        </complexContent>
      </complexType>
      <element name="GetServiceStatusRequest" type="EIPctym:GetServiceStatusRequestType"/>
      <element name="GetServiceStatusResponse" type="EIPctym:GetServiceStatusResponseType"/>
      <element name="GetReferenceDataRequest" type="EIPctym:GetReferenceDataRequestType"/>
      <element name="GetReferenceDataResponse" type="EIPctym:GetReferenceDataResponseType"/>
    </schema>
  </wsdl:types>
  <wsdl:message name="GetAggregatedReferenceDataResponse">
    <wsdl:part element="tns:GetAggregatedReferenceDataResponse" name="GetAggregatedReferenceDataResponse"></wsdl:part>
  </wsdl:message>
  <wsdl:message name="GetReferenceDataResponse">
    <wsdl:part element="sch4:GetReferenceDataResponse" name="GetReferenceDataResponse"></wsdl:part>
  </wsdl:message>
  <wsdl:message name="GetFlowReportResponse">
    <wsdl:part element="tns:GetFlowReportResponse" name="GetFlowReportResponse"></wsdl:part>
  </wsdl:message>
  <wsdl:message name="GetAggregatedReferenceDataRequest">
    <wsdl:part element="tns:GetAggregatedReferenceDataRequest" name="GetAggregatedReferenceDataRequest"></wsdl:part>
  </wsdl:message>
  <wsdl:message name="GetServiceStatusResponse">
    <wsdl:part element="sch4:GetServiceStatusResponse" name="GetServiceStatusResponse"></wsdl:part>
  </wsdl:message>
  <wsdl:message name="GetSystemUserReportResponse">
    <wsdl:part element="tns:GetSystemUserReportResponse" name="GetSystemUserReportResponse"></wsdl:part>
  </wsdl:message>
  <wsdl:message name="GetReferenceDataRequest">
    <wsdl:part element="sch4:GetReferenceDataRequest" name="GetReferenceDataRequest"></wsdl:part>
  </wsdl:message>
  <wsdl:message name="GetForwardedReferenceDataResponse">
    <wsdl:part element="tns:GetForwardedReferenceDataResponse" name="GetForwardedReferenceDataResponse"></wsdl:part>
  </wsdl:message>
  <wsdl:message name="GetFlowReportRequest">
    <wsdl:part element="tns:GetFlowReportRequest" name="GetFlowReportRequest"></wsdl:part>
  </wsdl:message>
  <wsdl:message name="GetSystemUserReportRequest">
    <wsdl:part element="tns:GetSystemUserReportRequest" name="GetSystemUserReportRequest"></wsdl:part>
  </wsdl:message>
  <wsdl:message name="GetForwardedReferenceDataRequest">
    <wsdl:part element="tns:GetForwardedReferenceDataRequest" name="GetForwardedReferenceDataRequest"></wsdl:part>
  </wsdl:message>
  <wsdl:message name="GetOperationReportResponse">
    <wsdl:part element="tns:GetOperationReportResponse" name="GetOperationReportResponse"></wsdl:part>
  </wsdl:message>
  <wsdl:message name="GetServiceStatusRequest">
    <wsdl:part element="sch4:GetServiceStatusRequest" name="GetServiceStatusRequest"></wsdl:part>
  </wsdl:message>
  <wsdl:message name="GetOperationReportRequest">
    <wsdl:part element="tns:GetOperationReportRequest" name="GetOperationReportRequest"></wsdl:part>
  </wsdl:message>
  <wsdl:portType name="iss.tech.support">
    <wsdl:operation name="GetAggregatedReferenceData">
      <wsdl:input message="tns:GetAggregatedReferenceDataRequest" name="GetAggregatedReferenceDataRequest"></wsdl:input>
      <wsdl:output message="tns:GetAggregatedReferenceDataResponse" name="GetAggregatedReferenceDataResponse"></wsdl:output>
    </wsdl:operation>
    <wsdl:operation name="GetReferenceData">
      <wsdl:input message="tns:GetReferenceDataRequest" name="GetReferenceDataRequest"></wsdl:input>
      <wsdl:output message="tns:GetReferenceDataResponse" name="GetReferenceDataResponse"></wsdl:output>
    </wsdl:operation>
    <wsdl:operation name="GetFlowReport">
      <wsdl:input message="tns:GetFlowReportRequest" name="GetFlowReportRequest"></wsdl:input>
      <wsdl:output message="tns:GetFlowReportResponse" name="GetFlowReportResponse"></wsdl:output>
    </wsdl:operation>
    <wsdl:operation name="GetServiceStatus">
      <wsdl:input message="tns:GetServiceStatusRequest" name="GetServiceStatusRequest"></wsdl:input>
      <wsdl:output message="tns:GetServiceStatusResponse" name="GetServiceStatusResponse"></wsdl:output>
    </wsdl:operation>
    <wsdl:operation name="GetSystemUserReport">
      <wsdl:input message="tns:GetSystemUserReportRequest" name="GetSystemUserReportRequest"></wsdl:input>
      <wsdl:output message="tns:GetSystemUserReportResponse" name="GetSystemUserReportResponse"></wsdl:output>
    </wsdl:operation>
    <wsdl:operation name="GetForwardedReferenceData">
      <wsdl:input message="tns:GetForwardedReferenceDataRequest" name="GetForwardedReferenceDataRequest"></wsdl:input>
      <wsdl:output message="tns:GetForwardedReferenceDataResponse" name="GetForwardedReferenceDataResponse"></wsdl:output>
    </wsdl:operation>
    <wsdl:operation name="GetOperationReport">
      <wsdl:input message="tns:GetOperationReportRequest" name="GetOperationReportRequest"></wsdl:input>
      <wsdl:output message="tns:GetOperationReportResponse" name="GetOperationReportResponse"></wsdl:output>
    </wsdl:operation>
  </wsdl:portType>
  <wsdl:binding name="iss.tech.supportSoap12" type="tns:iss.tech.support">
    <soap12:binding style="document" transport="http://schemas.xmlsoap.org/soap/http"/>
    <wsdl:operation name="GetAggregatedReferenceData">
      <soap12:operation soapAction=""/>
      <wsdl:input name="GetAggregatedReferenceDataRequest">
        <soap12:body use="literal"/>
      </wsdl:input>
      <wsdl:output name="GetAggregatedReferenceDataResponse">
        <soap12:body use="literal"/>
      </wsdl:output>
    </wsdl:operation>
    <wsdl:operation name="GetReferenceData">
      <soap12:operation soapAction=""/>
      <wsdl:input name="GetReferenceDataRequest">
        <soap12:body use="literal"/>
      </wsdl:input>
      <wsdl:output name="GetReferenceDataResponse">
        <soap12:body use="literal"/>
      </wsdl:output>
    </wsdl:operation>
    <wsdl:operation name="GetFlowReport">
      <soap12:operation soapAction=""/>
      <wsdl:input name="GetFlowReportRequest">
        <soap12:body use="literal"/>
      </wsdl:input>
      <wsdl:output name="GetFlowReportResponse">
        <soap12:body use="literal"/>
      </wsdl:output>
    </wsdl:operation>
    <wsdl:operation name="GetServiceStatus">
      <soap12:operation soapAction=""/>
      <wsdl:input name="GetServiceStatusRequest">
        <soap12:body use="literal"/>
      </wsdl:input>
      <wsdl:output name="GetServiceStatusResponse">
        <soap12:body use="literal"/>
      </wsdl:output>
    </wsdl:operation>
    <wsdl:operation name="GetSystemUserReport">
      <soap12:operation soapAction=""/>
      <wsdl:input name="GetSystemUserReportRequest">
        <soap12:body use="literal"/>
      </wsdl:input>
      <wsdl:output name="GetSystemUserReportResponse">
        <soap12:body use="literal"/>
      </wsdl:output>
    </wsdl:operation>
    <wsdl:operation name="GetForwardedReferenceData">
      <soap12:operation soapAction=""/>
      <wsdl:input name="GetForwardedReferenceDataRequest">
        <soap12:body use="literal"/>
      </wsdl:input>
      <wsdl:output name="GetForwardedReferenceDataResponse">
        <soap12:body use="literal"/>
      </wsdl:output>
    </wsdl:operation>
    <wsdl:operation name="GetOperationReport">
      <soap12:operation soapAction=""/>
      <wsdl:input name="GetOperationReportRequest">
        <soap12:body use="literal"/>
      </wsdl:input>
      <wsdl:output name="GetOperationReportResponse">
        <soap12:body use="literal"/>
      </wsdl:output>
    </wsdl:operation>
  </wsdl:binding>
  <wsdl:service name="iss.tech.supportService">
    <wsdl:port binding="tns:iss.tech.supportSoap12" name="iss.tech.supportSoap12">
      <soap12:address location="http://localhost:8080/platform-library-2.0.0/services/iss.tech.support"/>
    </wsdl:port>
  </wsdl:service>
</wsdl:definitions>]]></con:content><con:type>http://schemas.xmlsoap.org/wsdl/</con:type></con:part></con:definitionCache><con:endpoints><con:endpoint>http://localhost:8080/platform-library-2.0.0/services/iss.tech.support</con:endpoint></con:endpoints><con:operation isOneWay="false" action="" name="GetAggregatedReferenceData" bindingOperationName="GetAggregatedReferenceData" type="Request-Response" outputName="GetAggregatedReferenceDataResponse" inputName="GetAggregatedReferenceDataRequest" receivesAttachments="false" sendsAttachments="false" anonymous="optional"><con:settings/><con:call name="Request 1" wssPasswordType="PasswordDigest" outgoingWss="" incomingWss=""><con:settings><con:setting id="com.eviware.soapui.impl.wsdl.WsdlRequest@request-headers">&lt;xml-fragment/></con:setting></con:settings><con:encoding>UTF-8</con:encoding><con:endpoint>http://localhost:8080/platform-library-2.0.0/services/iss.tech.support</con:endpoint><con:request><![CDATA[<soap:Envelope xmlns:soap="http://www.w3.org/2003/05/soap-envelope" xmlns:tec="http://www.samples.com/TechnicalSupport/TechnicalSupportServiceMessages">
   <soap:Header/>
   <soap:Body>
      <tec:GetAggregatedReferenceDataRequest>
         <userName>?</userName>
         <criteria>
            <!--Zero or more repetitions:-->
            <id>?</id>
            <!--Optional:-->
            <maxElements>?</maxElements>
            <!--Optional:-->
            <category>?</category>
            <active>?</active>
         </criteria>
      </tec:GetAggregatedReferenceDataRequest>
   </soap:Body>
</soap:Envelope>]]></con:request><con:credentials><con:username>bus</con:username><con:password>password</con:password><con:domain xsi:nil="true"/><con:authType>No Authorization</con:authType></con:credentials><con:jmsConfig JMSDeliveryMode="PERSISTENT"/><con:jmsPropertyConfig/><con:wsaConfig mustUnderstand="NONE" version="200508" action="http://www.samples.com/TechnicalSupport/TechnicalSupportServiceMessages/iss.tech.support/GetAggregatedReferenceDataRequest"/><con:wsrmConfig version="1.2"/></con:call></con:operation><con:operation isOneWay="false" action="" name="GetReferenceData" bindingOperationName="GetReferenceData" type="Request-Response" outputName="GetReferenceDataResponse" inputName="GetReferenceDataRequest" receivesAttachments="false" sendsAttachments="false" anonymous="optional"><con:settings/><con:call name="Request 1" wssPasswordType="PasswordDigest" outgoingWss="" incomingWss=""><con:settings><con:setting id="com.eviware.soapui.impl.wsdl.WsdlRequest@request-headers">&lt;xml-fragment/></con:setting></con:settings><con:encoding>UTF-8</con:encoding><con:endpoint>http://localhost:8080/platform-library-2.0.0/services/iss.tech.support</con:endpoint><con:request><![CDATA[<soap:Envelope xmlns:soap="http://www.w3.org/2003/05/soap-envelope" xmlns:com="http://www.qpark.com/Common/CommonServiceMessages">
   <soap:Header/>
   <soap:Body>
      <com:GetReferenceDataRequest>
         <userName>?</userName>
         <criteria>
            <!--Zero or more repetitions:-->
            <id>?</id>
            <!--Optional:-->
            <maxElements>?</maxElements>
            <!--Optional:-->
            <category>?</category>
            <active>?</active>
         </criteria>
      </com:GetReferenceDataRequest>
   </soap:Body>
</soap:Envelope>]]></con:request><con:credentials><con:username>bus</con:username><con:password>password</con:password><con:domain xsi:nil="true"/><con:authType>No Authorization</con:authType></con:credentials><con:jmsConfig JMSDeliveryMode="PERSISTENT"/><con:jmsPropertyConfig/><con:wsaConfig mustUnderstand="NONE" version="200508" action="http://www.samples.com/TechnicalSupport/TechnicalSupportServiceMessages/iss.tech.support/GetReferenceDataRequest"/><con:wsrmConfig version="1.2"/></con:call></con:operation><con:operation isOneWay="false" action="" name="GetServiceStatus" bindingOperationName="GetServiceStatus" type="Request-Response" outputName="GetServiceStatusResponse" inputName="GetServiceStatusRequest" receivesAttachments="false" sendsAttachments="false" anonymous="optional"><con:settings/><con:call name="Request 1" wssPasswordType="PasswordDigest" outgoingWss="" incomingWss=""><con:settings><con:setting id="com.eviware.soapui.impl.wsdl.WsdlRequest@request-headers">&lt;xml-fragment/></con:setting></con:settings><con:encoding>UTF-8</con:encoding><con:endpoint>http://localhost:8080/platform-library-2.0.0/services/iss.tech.support</con:endpoint><con:request><![CDATA[<soap:Envelope xmlns:soap="http://www.w3.org/2003/05/soap-envelope" xmlns:com="http://www.qpark.com/Common/CommonServiceMessages">
   <soap:Header/>
   <soap:Body>
      <com:GetServiceStatusRequest>
         <userName>?</userName>
      </com:GetServiceStatusRequest>
   </soap:Body>
</soap:Envelope>]]></con:request><con:credentials><con:username>bus</con:username><con:password>password</con:password><con:domain xsi:nil="true"/><con:authType>No Authorization</con:authType></con:credentials><con:jmsConfig JMSDeliveryMode="PERSISTENT"/><con:jmsPropertyConfig/><con:wsaConfig mustUnderstand="NONE" version="200508" action="http://www.samples.com/TechnicalSupport/TechnicalSupportServiceMessages/iss.tech.support/GetServiceStatusRequest"/><con:wsrmConfig version="1.2"/></con:call></con:operation><con:operation isOneWay="false" action="" name="GetFlowReport" bindingOperationName="GetFlowReport" type="Request-Response" outputName="GetFlowReportResponse" inputName="GetFlowReportRequest" receivesAttachments="false" sendsAttachments="false" anonymous="optional"><con:settings/><con:call name="Request 1"><con:settings><con:setting id="com.eviware.soapui.impl.wsdl.WsdlRequest@request-headers">&lt;xml-fragment/></con:setting></con:settings><con:encoding>UTF-8</con:encoding><con:endpoint>http://localhost:8080/platform-library/services/iss.tech.support</con:endpoint><con:request><![CDATA[<soap:Envelope xmlns:soap="http://www.w3.org/2003/05/soap-envelope" xmlns:tec="http://www.samples.com/TechnicalSupport/TechnicalSupportServiceMessages">
   <soap:Header/>
   <soap:Body>
      <tec:GetFlowReportRequest>
         <userName>?</userName>
         <criteria>
            <start>?</start>
            <!--Optional:-->
            <end>?</end>
         </criteria>
      </tec:GetFlowReportRequest>
   </soap:Body>
</soap:Envelope>]]></con:request><con:credentials><con:authType>No Authorization</con:authType></con:credentials><con:jmsConfig JMSDeliveryMode="PERSISTENT"/><con:jmsPropertyConfig/><con:wsaConfig mustUnderstand="NONE" version="200508" action="http://www.samples.com/TechnicalSupport/TechnicalSupportServiceMessages/iss.tech.support/GetFlowReportRequest"/><con:wsrmConfig version="1.2"/></con:call></con:operation><con:operation isOneWay="false" action="" name="GetSystemUserReport" bindingOperationName="GetSystemUserReport" type="Request-Response" outputName="GetSystemUserReportResponse" inputName="GetSystemUserReportRequest" receivesAttachments="false" sendsAttachments="false" anonymous="optional"><con:settings/><con:call name="Request 1"><con:settings><con:setting id="com.eviware.soapui.impl.wsdl.WsdlRequest@request-headers">&lt;xml-fragment/></con:setting></con:settings><con:encoding>UTF-8</con:encoding><con:endpoint>http://localhost:8080/platform-library/services/iss.tech.support</con:endpoint><con:request><![CDATA[<soap:Envelope xmlns:soap="http://www.w3.org/2003/05/soap-envelope" xmlns:tec="http://www.samples.com/TechnicalSupport/TechnicalSupportServiceMessages">
   <soap:Header/>
   <soap:Body>
      <tec:GetSystemUserReportRequest>
         <userName>bhausen</userName>
         <criteria>
<date>2015-11-26</date>
</criteria>
      </tec:GetSystemUserReportRequest>
   </soap:Body>
</soap:Envelope>]]></con:request><con:credentials><con:authType>No Authorization</con:authType></con:credentials><con:jmsConfig JMSDeliveryMode="PERSISTENT"/><con:jmsPropertyConfig/><con:wsaConfig mustUnderstand="NONE" version="200508" action="http://www.samples.com/TechnicalSupport/TechnicalSupportServiceMessages/iss.tech.support/GetSystemUserReportRequest"/><con:wsrmConfig version="1.2"/></con:call></con:operation><con:operation isOneWay="false" action="" name="GetForwardedReferenceData" bindingOperationName="GetForwardedReferenceData" type="Request-Response" outputName="GetForwardedReferenceDataResponse" inputName="GetForwardedReferenceDataRequest" receivesAttachments="false" sendsAttachments="false" anonymous="optional"><con:settings/><con:call name="Request 1"><con:settings/><con:encoding>UTF-8</con:encoding><con:endpoint>http://localhost:8080/platform-library-2.0.0/services/iss.tech.support</con:endpoint><con:request><![CDATA[<soap:Envelope xmlns:soap="http://www.w3.org/2003/05/soap-envelope" xmlns:tec="http://www.samples.com/TechnicalSupport/TechnicalSupportServiceMessages">
   <soap:Header/>
   <soap:Body>
      <tec:GetForwardedReferenceDataRequest>
         <userName>?</userName>
         <criteria>
            <!--Zero or more repetitions:-->
            <id>?</id>
            <!--Optional:-->
            <maxElements>?</maxElements>
            <!--Optional:-->
            <category>?</category>
            <active>?</active>
         </criteria>
      </tec:GetForwardedReferenceDataRequest>
   </soap:Body>
</soap:Envelope>]]></con:request><con:wsaConfig mustUnderstand="NONE" version="200508" action="http://www.samples.com/TechnicalSupport/TechnicalSupportServiceMessages/iss.tech.support/GetForwardedReferenceDataRequest"/></con:call></con:operation><con:operation isOneWay="false" action="" name="GetOperationReport" bindingOperationName="GetOperationReport" type="Request-Response" outputName="GetOperationReportResponse" inputName="GetOperationReportRequest" receivesAttachments="false" sendsAttachments="false" anonymous="optional"><con:settings/><con:call name="Request 1"><con:settings/><con:encoding>UTF-8</con:encoding><con:endpoint>http://localhost:8080/platform-library-2.0.0/services/iss.tech.support</con:endpoint><con:request><![CDATA[<soap:Envelope xmlns:soap="http://www.w3.org/2003/05/soap-envelope" xmlns:tec="http://www.samples.com/TechnicalSupport/TechnicalSupportServiceMessages">
   <soap:Header/>
   <soap:Body>
      <tec:GetOperationReportRequest>
         <userName>?</userName>
         <criteria>
            <!--Optional:-->
            <service>?</service>
            <!--Optional:-->
            <operation>?</operation>
            <!--Optional:-->
            <consumerName>?</consumerName>
         </criteria>
      </tec:GetOperationReportRequest>
   </soap:Body>
</soap:Envelope>]]></con:request><con:wsaConfig mustUnderstand="NONE" version="200508" action="http://www.samples.com/TechnicalSupport/TechnicalSupportServiceMessages/iss.tech.support/GetOperationReportRequest"/></con:call></con:operation></con:interface><con:endpointStrategy xsi:type="con:DefaultEndpointStrategy" xmlns:xsi="http://www.w3.org/2001/XMLSchema-instance"><con:endpoint mode="COMPLEMENT" username="bus" password="password" wssType="PasswordDigest">http://localhost:8080/platform-library-2.0.0/services/library</con:endpoint><con:endpoint mode="COMPLEMENT" username="bus" password="password" wssType="PasswordDigest">http://localhost:8080/platform-library-2.0.0/services/iss.common</con:endpoint><con:endpoint mode="COMPLEMENT" username="bus" password="password" wssType="PasswordDigest">http://localhost:8080/platform-library-2.0.0/services/iss.tech.support</con:endpoint><con:endpoint mode="COMPLEMENT" username="bus" password="password" wssType="PasswordDigest">http://localhost:8080/platform-library-2.1.0/services/library</con:endpoint></con:endpointStrategy><con:properties/><con:wssContainer/><con:oAuth2ProfileContainer/></con:soapui-project>